k8ssetup/VERSION.txt
k8ssetup/__init__.py
k8ssetup/cert.py
k8ssetup/cli.py
k8ssetup/consts.py
k8ssetup/context.py
k8ssetup/generator.py
k8ssetup/info.py
k8ssetup/provision.py
k8ssetup/tool.py
k8ssetup/version.py
k8ssetup/conf/defaults.yml
k8ssetup/conf/vagrant.yml
k8ssetup/lib/scratchpad.md
k8ssetup/lib/ansible/cluster-local.yml
k8ssetup/lib/ansible/cluster.yml
k8ssetup/lib/ansible/firewall-rules-clp.yml
k8ssetup/lib/ansible/firewall-rules-wrk.yml
k8ssetup/lib/ansible/hosts.yml
k8ssetup/lib/ansible/incluster.yml
k8ssetup/lib/ansible/vagrantpp.yml
k8ssetup/lib/ansible/library/testinput
k8ssetup/lib/ansible/library/wd_helm3.py
k8ssetup/lib/ansible/library/wd_k8snamespace.py
k8ssetup/lib/ansible/library/wd_script_action.py
k8ssetup/lib/ansible/library/wd_script_module.py
k8ssetup/lib/ansible/localtemplates/configure-trident
k8ssetup/lib/ansible/localtemplates/import-admin.conf
k8ssetup/lib/ansible/localtemplates/install-tools
k8ssetup/lib/ansible/localtemplates/trident-standard-storageclass.yaml
k8ssetup/lib/ansible/localtemplates/use-context
k8ssetup/lib/ansible/localtemplates/write-k8s-setup-info
k8ssetup/lib/ansible/roles/readme.md
k8ssetup/lib/ansible/roles/lnx-setup/handlers/main.yml
k8ssetup/lib/ansible/roles/lnx-setup/tasks/main.yml
k8ssetup/lib/ansible/roles/lnx-setup/templates/demon.json
k8ssetup/lib/ansible/roles/lnxclp-first/tasks/main.yml
k8ssetup/lib/ansible/roles/lnxclp-new/tasks/main.yml
k8ssetup/lib/ansible/roles/lnxclp-setup/tasks/main.yml
k8ssetup/lib/ansible/roles/lnxclp-vip/readme.md
k8ssetup/lib/ansible/roles/lnxclp-vip/tasks/main.yml
k8ssetup/lib/ansible/roles/lnxclp-vip/templates/haproxy.cfg
k8ssetup/lib/ansible/roles/lnxclp-vip/templates/keepalived.conf
k8ssetup/lib/ansible/roles/lnxkubeadm-common/tasks/main.yml
k8ssetup/lib/ansible/roles/lnxkubeadm-common/templates/k8s-setup
k8ssetup/lib/ansible/roles/lnxkubeadm-common/templates/k8s-setup.env
k8ssetup/lib/ansible/roles/lnxkubeadm-common/templates/kubeadm-initconfig.yaml
k8s_setup-0.2.3.dev0.dist-info/METADATA
k8s_setup-0.2.3.dev0.dist-info/WHEEL
k8s_setup-0.2.3.dev0.dist-info/entry_points.txt
k8s_setup-0.2.3.dev0.dist-info/top_level.txt
k8s_setup-0.2.3.dev0.dist-info/RECORD
