Metadata-Version: 2.1
Name: k8s-setup
Version: 0.2.3.dev0
Summary: Setup local and production hybrid clusters, using Ansible and Vagrant
Home-page: https://github.com/world-direct/k8s-setup
Author: gprossliner
Author-email: createissue@github.com
License: UNKNOWN
Platform: UNKNOWN
Requires-Dist: click (>=7.0)
Requires-Dist: ansible (>=2.8.6)
Requires-Dist: kubernetes (>=10.0)
Requires-Dist: colorlog (>=4.1.0)
Requires-Dist: pyyaml (>=5.2)
Requires-Dist: jmespath (>=0.10.0)
